Metadata-Version: 2.1
Name: dbfwrite
Version: 0.1
Summary: A package for converting dataframe to DBF file
Home-page: https://github.com/vanelwy
Author: Wenyu Li
Author-email: vanelwy@gmail.com
License: UNKNOWN
Platform: UNKNOWN
Classifier: Programming Language :: Python :: 3.7
Classifier: License :: OSI Approved :: MIT License
Classifier: Operating System :: Microsoft
Requires-Python: >=3.0
